pymusixmatch/__init__.py
pymusixmatch/enums.py
pymusixmatch/musixmatch.py
pymusixmatch-0.1.4.dist-info/LICENSE
pymusixmatch-0.1.4.dist-info/METADATA
pymusixmatch-0.1.4.dist-info/WHEEL
pymusixmatch-0.1.4.dist-info/RECORD
